spork/__about__.py
spork/__init__.py
spork/decorators.py
spork/models.py
spork/protocols.py
spork/py.typed
spork-1.2.0.dist-info/METADATA
spork-1.2.0.dist-info/WHEEL
spork-1.2.0.dist-info/licenses/LICENSE.txt
spork-1.2.0.dist-info/RECORD
