Metadata-Version: 2.1
Name: spork
Version: 1.2.0
Project-URL: Documentation, https://github.com/rgbkrk/spork#readme
Project-URL: Issues, https://github.com/rgbkrk/spork/issues
Project-URL: Source, https://github.com/rgbkrk/spork
Author-email: Kyle Kelley <rgbkrk@gmail.com>
License-Expression: MIT
License-File: LICENSE.txt
Classifier: Development Status :: 4 - Beta
Classifier: Programming Language :: Python
Classifier: Programming Language :: Python :: 3.9
Classifier: Programming Language :: Python :: 3.10
Classifier: Programming Language :: Python :: 3.11
Classifier: Programming Language :: Python :: 3.12
Classifier: Programming Language :: Python :: Implementation :: CPython
Classifier: Programming Language :: Python :: Implementation :: PyPy
Requires-Python: >=3.9
Requires-Dist: ipython
Requires-Dist: pydantic
Requires-Dist: typing-extensions
